simplipy/__init__.py
simplipy/api.py
simplipy/const.py
simplipy/device/__init__.py
simplipy/device/camera.py
simplipy/device/lock.py
simplipy/device/sensor/__init__.py
simplipy/device/sensor/v2.py
simplipy/device/sensor/v3.py
simplipy/errors.py
simplipy/py.typed
simplipy/system/__init__.py
simplipy/system/v2.py
simplipy/system/v3.py
simplipy/util/__init__.py
simplipy/util/auth.py
simplipy/util/dt.py
simplipy/util/string.py
simplipy/websocket.py
simplisafe_python-2024.1.0.dist-info/LICENSE
simplisafe_python-2024.1.0.dist-info/METADATA
simplisafe_python-2024.1.0.dist-info/WHEEL
simplisafe_python-2024.1.0.dist-info/RECORD
