Metadata-Version: 2.1
Name: simplisafe-python
Version: 2024.1.0
Summary: A Python3, async interface to the SimpliSafe API
Home-page: https://github.com/bachya/simplisafe-python
License: MIT
Author: Aaron Bach
Author-email: bachya1208@gmail.com
Requires-Python: >=3.10,<4.0
Classifier: License :: OSI Approved :: MIT License
Classifier: Programming Language :: Python
Classifier: Programming Language :: Python :: 3
Classifier: Programming Language :: Python :: 3.10
Classifier: Programming Language :: Python :: 3.11
Classifier: Programming Language :: Python :: 3.12
Classifier: Programming Language :: Python :: Implementation :: CPython
Classifier: Programming Language :: Python :: Implementation :: PyPy
Requires-Dist: aiohttp (>=3.9.0b0)
Requires-Dist: backoff (>=1.11.1)
Requires-Dist: certifi (>=2023.07.22)
Requires-Dist: voluptuous (>=0.11.7)
Requires-Dist: websockets (>=8.1)
Requires-Dist: yarl (>=1.9.2)
Project-URL: Bug Tracker, https://github.com/bachya/simplipy/issues
Project-URL: Changelog, https://github.com/bachya/simplipy/releases
Project-URL: Repository, https://github.com/bachya/simplisafe-python
